image_puzzle_game/__init__.py
image_puzzle_game/demo.ipynb
image_puzzle_game/game.py
image_puzzle_game-1.0.0.dist-info/METADATA
image_puzzle_game-1.0.0.dist-info/WHEEL
image_puzzle_game-1.0.0.dist-info/licenses/LICENSE
image_puzzle_game-1.0.0.dist-info/RECORD
