Metadata-Version: 2.1
Name: image_puzzle_game
Version: 1.0.0
Summary: A 3x3 grid image puzzle game built using the Pillow library.
Project-URL: Homepage, https://github.com/francisohara24/image-puzzle-game
Project-URL: Bug Tracker, https://github.com/francisohara24/image-puzzle-game/issues
Author-email: Francis O'Hara <franciskohara@gmail.com>
License-File: LICENSE
Keywords: game,games,image,jupyter,notebook,pillow,play,puzzle
Classifier: License :: OSI Approved :: MIT License
Classifier: Operating System :: OS Independent
Classifier: Programming Language :: Python :: 3
Requires-Python: >=3.10
